TruthTorchLM/__init__.py
TruthTorchLM/availability.py
TruthTorchLM/calibration.py
TruthTorchLM/environment.py
TruthTorchLM/error_handler.py
TruthTorchLM/generation.py
TruthTorchLM/templates.py
TruthTorchLM/evaluators/__init__.py
TruthTorchLM/evaluators/bleu.py
TruthTorchLM/evaluators/correctness_evaluator.py
TruthTorchLM/evaluators/eval_truth_method.py
TruthTorchLM/evaluators/model_judge.py
TruthTorchLM/evaluators/rouge.py
TruthTorchLM/long_form_generation/__init__.py
TruthTorchLM/long_form_generation/generation.py
TruthTorchLM/long_form_generation/templates.py
TruthTorchLM/long_form_generation/claim_check_methods/__init__.py
TruthTorchLM/long_form_generation/claim_check_methods/answer_claim_entailment.py
TruthTorchLM/long_form_generation/claim_check_methods/claim_check_method.py
TruthTorchLM/long_form_generation/claim_check_methods/naive_application.py
TruthTorchLM/long_form_generation/claim_check_methods/question_answer_generation.py
TruthTorchLM/long_form_generation/claim_check_methods/question_generation.py
TruthTorchLM/long_form_generation/decomposition_methods/__init__.py
TruthTorchLM/long_form_generation/decomposition_methods/decomposition_method.py
TruthTorchLM/long_form_generation/decomposition_methods/structured_decomposition_api.py
TruthTorchLM/long_form_generation/decomposition_methods/structured_decomposition_local.py
TruthTorchLM/long_form_generation/decomposition_methods/unstructured_decomposition_api.py
TruthTorchLM/long_form_generation/decomposition_methods/unstructured_decomposition_local.py
TruthTorchLM/long_form_generation/evaluators/__init__.py
TruthTorchLM/long_form_generation/evaluators/eval_claim.py
TruthTorchLM/long_form_generation/evaluators/long_gen_eval.py
TruthTorchLM/long_form_generation/utils/__init__.py
TruthTorchLM/long_form_generation/utils/dataset_utils.py
TruthTorchLM/long_form_generation/utils/eval_utils.py
TruthTorchLM/long_form_generation/utils/safe_utils.py
TruthTorchLM/normalizers/__init__.py
truthtorchlm-0.1.17.dist-info/LICENSE
truthtorchlm-0.1.17.dist-info/METADATA
truthtorchlm-0.1.17.dist-info/WHEEL
truthtorchlm-0.1.17.dist-info/top_level.txt
truthtorchlm-0.1.17.dist-info/RECORD
