Metadata-Version: 2.2
Name: TruthTorchLM
Version: 0.1.17
Summary: TruthTorchLM is an open-source library designed to assess truthfulness in language models' outputs. The library integrates state-of-the-art methods, offers comprehensive benchmarking tools across various tasks, and enables seamless integration with popular frameworks like Huggingface and LiteLLM.
Author: Yavuz Faruk Bakman
Author-email: ybakman@usc.edu
Requires-Python: >=3.10
License-File: LICENSE
Requires-Dist: aiohttp
Requires-Dist: evaluate
Requires-Dist: instructor
Requires-Dist: litellm
Requires-Dist: nest_asyncio
Requires-Dist: numpy
Requires-Dist: outlines
Requires-Dist: pandas
Requires-Dist: pydantic
Requires-Dist: PyYAML
Requires-Dist: Requests
Requires-Dist: scikit_learn
Requires-Dist: scipy
Requires-Dist: sentence_transformers
Requires-Dist: termcolor
Requires-Dist: torch
Requires-Dist: tqdm
Requires-Dist: transformers
Requires-Dist: absl-py
Requires-Dist: nltk
Requires-Dist: rouge_score
Requires-Dist: wandb
Requires-Dist: sentencepiece
Requires-Dist: accelerate>=0.26.0
Dynamic: author
Dynamic: author-email
Dynamic: description
Dynamic: description-content-type
Dynamic: requires-dist
Dynamic: requires-python
Dynamic: summary
